scalyca/__init__.py
scalyca/colour.py
scalyca/configuration.py
scalyca/exceptions.py
scalyca/logger.py
scalyca/scala.py
scalyca/scalyca.py
scalyca/utilities.py
scalyca-0.2.7.dist-info/METADATA
scalyca-0.2.7.dist-info/WHEEL
scalyca-0.2.7.dist-info/licenses/LICENSE
scalyca-0.2.7.dist-info/RECORD
