Metadata-Version: 2.4
Name: scalyca
Version: 0.2.7
Summary: Simple Console Application with Logging, Yaml Configuration and Argparse
License-File: LICENSE
Author: Martin Baláž
Author-email: martin.balaz@trojsten.sk
Requires-Python: <4.0,>=3.10
Classifier: Programming Language :: Python :: 3
Classifier: Programming Language :: Python :: 3.10
Classifier: Programming Language :: Python :: 3.11
Classifier: Programming Language :: Python :: 3.12
Classifier: Programming Language :: Python :: 3.13
Classifier: Programming Language :: Python :: 3.14
Requires-Dist: argparse
Requires-Dist: argparsedirs (>=0.2.0,<0.3.0)
Requires-Dist: colorama
Requires-Dist: dotmap (>=1.3.30,<2.0.0)
Requires-Dist: pyyaml
Requires-Dist: schema (>=0.7.7,<0.8.0)
Project-URL: Homepage, https://github.com/sesquideus/scalyca
